moin/__init__.py
moin/_template.py
moin/_version.py
moin/app.py
moin/conftest.py
moin/error.py
moin/forms.py
moin/log.py
moin/user.py
moin/wikiutil.py
moin/_tests/__init__.py
moin/_tests/_test_template.py
moin/_tests/ldap_testbase.py
moin/_tests/ldap_testdata.py
moin/_tests/test_error.py
moin/_tests/test_forms.py
moin/_tests/test_logging.conf
moin/_tests/test_test_environ.py
moin/_tests/test_user.py
moin/_tests/test_views.py
moin/_tests/test_wikiutil.py
moin/_tests/wikiconfig.py
moin/_tests/wiki/data/plugin/__init__.py
moin/apps/__init__.py
moin/apps/admin/__init__.py
moin/apps/admin/views.py
moin/apps/admin/_tests/test_admin.py
moin/apps/admin/templates/admin/group_acl_report.html
moin/apps/admin/templates/admin/groupbrowser.html
moin/apps/admin/templates/admin/index.html
moin/apps/admin/templates/admin/item_acl_report.html
moin/apps/admin/templates/admin/register_new_user.html
moin/apps/admin/templates/admin/trash.html
moin/apps/admin/templates/admin/user_acl_report.html
moin/apps/admin/templates/admin/userbrowser.html
moin/apps/admin/templates/admin/wikiconfig.html
moin/apps/admin/templates/admin/wikiconfighelp.html
moin/apps/admin/templates/user/highlighterhelp.html
moin/apps/admin/templates/user/index_user.html
moin/apps/admin/templates/user/interwikihelp.html
moin/apps/admin/templates/user/itemsize.html
moin/apps/feed/__init__.py
moin/apps/feed/views.py
moin/apps/feed/_tests/test_feed.py
moin/apps/frontend/__init__.py
moin/apps/frontend/views.py
moin/apps/frontend/_tests/test_frontend.py
moin/apps/misc/__init__.py
moin/apps/misc/views.py
moin/apps/misc/_tests/test_misc.py
moin/apps/misc/templates/misc/sitemap.xml
moin/apps/misc/templates/misc/urls_names.txt
moin/apps/serve/__init__.py
moin/apps/serve/views.py
moin/apps/serve/_tests/test_serve.py
moin/auth/__init__.py
moin/auth/http.py
moin/auth/ldap_login.py
moin/auth/log.py
moin/auth/_tests/test_auth.py
moin/auth/_tests/test_http.py
moin/auth/_tests/test_ldap_login.py
moin/auth/_tests/test_log.py
moin-2.0.0b4.dist-info/licenses/LICENSE.txt
moin-2.0.0b4.dist-info/METADATA
moin-2.0.0b4.dist-info/WHEEL
moin-2.0.0b4.dist-info/entry_points.txt
moin-2.0.0b4.dist-info/top_level.txt
moin-2.0.0b4.dist-info/RECORD
