Metadata-Version: 2.4
Name: moin
Version: 2.0.0b4
Summary: MoinMoin is an easy to use, full-featured and extensible wiki software package
Author: Juergen Hermann et al.
Maintainer-email: RogerHaase <haaserd@gmail.com>, Thomas Waldmann <tw@waldmann-edv.de>
License-Expression: GPL-2.0-or-later
Project-URL: Homepage, https://moinmo.in/
Project-URL: Bug Tracker, https://github.com/moinwiki/moin/issues
Project-URL: Documentation, https://moin-20.readthedocs.io/
Project-URL: Repository, https://github.com/moinwiki/moin
Project-URL: Changelog, https://github.com/moinwiki/moin/blob/master/docs/changes/CHANGES
Keywords: wiki,web
Classifier: Development Status :: 4 - Beta
Classifier: Environment :: Web Environment
Classifier: Intended Audience :: Education
Classifier: Intended Audience :: End Users/Desktop
Classifier: Intended Audience :: Information Technology
Classifier: Intended Audience :: Other Audience
Classifier: Intended Audience :: Science/Research
Classifier: Natural Language :: English
Classifier: Operating System :: OS Independent
Classifier: Programming Language :: Python
Classifier: Programming Language :: Python :: 3
Classifier: Programming Language :: Python :: 3.10
Classifier: Programming Language :: Python :: 3.11
Classifier: Programming Language :: Python :: 3.12
Classifier: Programming Language :: Python :: 3.13
Classifier: Programming Language :: Python :: 3.14
Classifier: Topic :: Internet :: WWW/HTTP :: WSGI
Classifier: Topic :: Internet :: WWW/HTTP :: WSGI :: Application
Classifier: Topic :: Internet :: WWW/HTTP :: Dynamic Content
Classifier: Topic :: Office/Business :: Groupware
Classifier: Topic :: Text Processing :: Markup
Requires-Python: >=3.10
License-File: LICENSE.txt
Requires-Dist: Babel>=2.16.0
Requires-Dist: blinker>=1.6.2
Requires-Dist: docutils>=0.18.1
Requires-Dist: Markdown>=3.4.1
Requires-Dist: mdx_wikilink_plus>=1.4.1
Requires-Dist: Flask>=3.0.0
Requires-Dist: Flask-Babel>=3.0.0
Requires-Dist: Flask-Caching>=1.2.0
Requires-Dist: Flask-Theme>=0.3.6
Requires-Dist: emeraldtree>=0.10.0
Requires-Dist: feedgen>=0.9.0
Requires-Dist: flatland>=0.8
Requires-Dist: Jinja2>=3.1.0
Requires-Dist: markupsafe>=3.0.2
Requires-Dist: pygments>=1.4
Requires-Dist: Werkzeug>=3.0.0
Requires-Dist: whoosh>=2.7.0
Requires-Dist: pdfminer.six
Requires-Dist: passlib>=1.6.0
Requires-Dist: sqlalchemy>=2.0
Requires-Dist: typing_extensions>=4.12.2
Requires-Dist: XStatic<2.0.0,>=0.0.2
Requires-Dist: XStatic-Bootstrap<=4.5.3.1,>=4.5.3.1
Requires-Dist: XStatic-Font-Awesome<=6.2.1.1,>=6.2.1.0
Requires-Dist: XStatic-CKEditor<=3.6.4.0,>=3.6.1.2
Requires-Dist: XStatic-autosize<=1.17.2.1
Requires-Dist: XStatic-jQuery<=3.5.1.1,>=1.8.2
Requires-Dist: XStatic-jQuery-File-Upload<=10.31.0.1,>=10.31.0
Requires-Dist: XStatic-svg-edit-moin<=2012.11.27.1,>=2012.11.15.1
Requires-Dist: XStatic-JQuery.TableSorter<=2.14.5.2,>=2.14.5.1
Requires-Dist: XStatic-Pygments<=2.9.0.1,>=1.6.0.1
Provides-Extra: pillow
Requires-Dist: pillow; extra == "pillow"
Provides-Extra: ldap
Requires-Dist: python-ldap; extra == "ldap"
Dynamic: license-file
